bumerge.py
bumerge-0.2.1.dist-info/METADATA
bumerge-0.2.1.dist-info/WHEEL
bumerge-0.2.1.dist-info/entry_points.txt
bumerge-0.2.1.dist-info/licenses/LICENSE
bumerge-0.2.1.dist-info/RECORD
