Metadata-Version: 2.3
Name: bumerge
Version: 0.2.1
Summary: Merge Butane configurations
Project-URL: Bug tracker, https://github.com/kytta/bumerge/issues
Project-URL: Changelog, https://github.com/kytta/bumerge/blob/main/CHANGELOG.md
Project-URL: Funding, https://github.com/sponsors/kytta
Project-URL: Source Code, https://github.com/kytta/bumerge/
Author-email: Nikita Karamov <me@kytta.dev>
Maintainer-email: Nikita Karamov <me@kytta.dev>
License: BSD-3-Clause
License-File: LICENSE
Classifier: Development Status :: 3 - Alpha
Classifier: Environment :: Console
Classifier: Intended Audience :: System Administrators
Classifier: License :: OSI Approved :: BSD License
Classifier: Operating System :: OS Independent
Classifier: Programming Language :: Python :: 3 :: Only
Classifier: Programming Language :: Python :: 3.9
Classifier: Programming Language :: Python :: 3.10
Classifier: Programming Language :: Python :: 3.11
Classifier: Programming Language :: Python :: 3.12
Classifier: Programming Language :: Python :: 3.13
Classifier: Topic :: System :: Systems Administration
Classifier: Typing :: Typed
Requires-Python: >=3.9
Requires-Dist: ruamel-yaml>=0.15
